jarvan/__init__.py
jarvan/common.py
jarvan/db.py
jarvan/helper.py
jarvan/j.py
jarvan/kms.py
jarvan/kms_helper.py
jarvan/login.py
jarvan/router.py
jumperpy/__init__.py
jumperpy/db.py
jumperpy/helper.py
jumperpy/kms.py
jumperpy/kms_helper.py
jumperpy/login.py
jarvan-0.0.9.dist-info/LICENSE
jarvan-0.0.9.dist-info/METADATA
jarvan-0.0.9.dist-info/WHEEL
jarvan-0.0.9.dist-info/top_level.txt
jarvan-0.0.9.dist-info/RECORD
